{
  "channel_id": "rewind_retro_media",
  "channel_name": "Rewind Retro Media",
  "github_environment": "Rewind Retro Media",
  "category": "Entertainment",
  "youtube_category_id": "24",
  "default_tags": [
    "nostalgia",
    "retro",
    "90s",
    "2000s",
    "throwback",
    "vintage",
    "shorts"
  ],
  "pexels_search_prefix": "vintage retro",
  "music_mood": "upbeat",
  "topics": [
    {
      "id": 1,
      "title": "When Blockbuster Was King",
      "hook": "What Killed The Blockbuster Empire...",
      "status": "published",
      "published_date": "2026-02-13T20:24:47.079453+00:00",
      "video_id": "ASbAph4tlwg"
    },
    {
      "id": 2,
      "title": "The Flip Phone Era",
      "hook": "What Killed The Flip Phone...",
      "status": "published",
      "published_date": "2026-02-15T08:19:40.119712+00:00",
      "video_id": "EZfQgxlaKEM"
    },
    {
      "id": 3,
      "title": "MySpace Top 8 Drama",
      "hook": "What Ruined Friendships On MySpace...",
      "status": "published",
      "published_date": "2026-02-15T20:14:16.064332+00:00",
      "video_id": "9nr3vIVayMs"
    },
    {
      "id": 4,
      "title": "Dial Up Internet Sounds",
      "hook": "What Haunts 90s Kids Forever...",
      "status": "published",
      "published_date": "2026-02-16T08:34:04.007092+00:00",
      "video_id": "7NrJpbg8ZKU"
    },
    {
      "id": 5,
      "title": "Rewinding VHS Tapes",
      "hook": "What Happens When You Rewind...",
      "status": "published",
      "published_date": "2026-02-16T20:20:20.631539+00:00",
      "video_id": "X4rAgKcOqis"
    },
    {
      "id": 6,
      "title": "Nokia 3310 Indestructible",
      "hook": "What Cant Kill Nokia 3310...",
      "status": "published",
      "published_date": "2026-02-17T08:32:36.958714+00:00",
      "video_id": "9B4aJvnN5ic"
    },
    {
      "id": 7,
      "title": "Limewire Virus Hell",
      "hook": "What Killed 100 Million Family Computers...",
      "status": "published",
      "published_date": "2026-02-17T20:27:21.537604+00:00",
      "video_id": "mk1jL1pVsE8"
    },
    {
      "id": 8,
      "title": "AOL Instant Messenger Away Messages",
      "hook": "What Did AIM Away Messages Reveal...",
      "status": "published",
      "published_date": "2026-02-18T08:33:15.589580+00:00",
      "video_id": "coqBI9SkrFI"
    },
    {
      "id": 9,
      "title": "Burning CDs For Friends",
      "hook": "What Made Burning CDs So Special...",
      "status": "pending",
      "published_date": null,
      "video_id": null
    },
    {
      "id": 10,
      "title": "MapQuest Printed Directions",
      "hook": "What Made MapQuest So Inaccurate...",
      "status": "pending",
      "published_date": null,
      "video_id": null
    },
    {
      "id": 11,
      "title": "Tamagotchi Deaths",
      "hook": "What Killed Your Tamagotchi Always...",
      "status": "pending",
      "published_date": null,
      "video_id": null
    },
    {
      "id": 12,
      "title": "Calling Landlines Nervously",
      "hook": "What Happens When You Call...",
      "status": "pending",
      "published_date": null,
      "video_id": null
    },
    {
      "id": 13,
      "title": "Waiting For Photos To Develop",
      "hook": "What Happens When Photos Never Develop...",
      "status": "pending",
      "published_date": null,
      "video_id": null
    },
    {
      "id": 14,
      "title": "TV Guide Channel Wait",
      "hook": "What Made TV Guide Wait So...",
      "status": "pending",
      "published_date": null,
      "video_id": null
    },
    {
      "id": 15,
      "title": "Scholastic Book Fair Chaos",
      "hook": "What Happens At Scholastic Book Fairs...",
      "status": "pending",
      "published_date": null,
      "video_id": null
    },
    {
      "id": 16,
      "title": "Pencil And Cassette Tape Trick",
      "hook": "How Did Pencils Fix Cassette Tapes...",
      "status": "pending",
      "published_date": null,
      "video_id": null
    },
    {
      "id": 17,
      "title": "Oregon Trail School Computer Game",
      "hook": "What Killed 90% Of Pioneers...",
      "status": "pending",
      "published_date": null,
      "video_id": null
    },
    {
      "id": 18,
      "title": "Encarta Encyclopedia CD-ROM",
      "hook": "What Killed Microsoft Encarta...",
      "status": "pending",
      "published_date": null,
      "video_id": null
    },
    {
      "id": 19,
      "title": "Razor Scooter Ankle Destruction",
      "hook": "What Destroys Ankles On Razor Scooters...",
      "status": "pending",
      "published_date": null,
      "video_id": null
    },
    {
      "id": 20,
      "title": "Heelys Banned From School",
      "hook": "What Made Heelys Forbidden At Schools...",
      "status": "pending",
      "published_date": null,
      "video_id": null
    },
    {
      "id": 21,
      "title": "iPod Shuffle Random Confusion",
      "hook": "What Made iPod Shuffle So Confusing...",
      "status": "pending",
      "published_date": null,
      "video_id": null
    },
    {
      "id": 22,
      "title": "Walkman Cassette Player",
      "hook": "What Killed Your Favorite Cassette...",
      "status": "pending",
      "published_date": null,
      "video_id": null
    },
    {
      "id": 23,
      "title": "Floppy Disk Save Icon",
      "hook": "What Do Floppy Disks Really Save...",
      "status": "pending",
      "published_date": null,
      "video_id": null
    },
    {
      "id": 24,
      "title": "Skipping Burned CDs In Car",
      "hook": "What Causes Burned CDs To Always Skip...",
      "status": "pending",
      "published_date": null,
      "video_id": null
    },
    {
      "id": 25,
      "title": "Low Battery Beep Game Boy",
      "hook": "What Does Game Boy Beep Mean...",
      "status": "pending",
      "published_date": null,
      "video_id": null
    },
    {
      "id": 26,
      "title": "Nintendo Cartridge Blowing Myth",
      "hook": "What Never Fixed Nintendo Cartridges...",
      "status": "pending",
      "published_date": null,
      "video_id": null
    },
    {
      "id": 27,
      "title": "Nickelodeon Slime Everywhere",
      "hook": "What Happens When Slime Never Ends...",
      "status": "pending",
      "published_date": null,
      "video_id": null
    },
    {
      "id": 28,
      "title": "Dunkaroos Lunch Box Treasure",
      "hook": "What Made Dunkaroos So Rare...",
      "status": "pending",
      "published_date": null,
      "video_id": null
    },
    {
      "id": 29,
      "title": "Lunchables Trading Economy",
      "hook": "What Fuels Lunchables Black Market...",
      "status": "pending",
      "published_date": null,
      "video_id": null
    },
    {
      "id": 30,
      "title": "Capri Sun Straw Struggle",
      "hook": "What Makes Capri Sun Straws Impossible...",
      "status": "pending",
      "published_date": null,
      "video_id": null
    },
    {
      "id": 31,
      "title": "Waiting For Saturday Morning Cartoons",
      "hook": "What Killed Saturday Morning Cartoons...",
      "status": "pending",
      "published_date": null,
      "video_id": null
    },
    {
      "id": 32,
      "title": "One TV Remote War",
      "hook": "What Causes Remote Control Wars...",
      "status": "pending",
      "published_date": null,
      "video_id": null
    },
    {
      "id": 33,
      "title": "VCR Recording Timer Confusion",
      "hook": "What Cant Parents Set On VCRs...",
      "status": "pending",
      "published_date": null,
      "video_id": null
    },
    {
      "id": 34,
      "title": "Blank VHS Recording Over Memories",
      "hook": "What Gets Erased Forever On VHS...",
      "status": "pending",
      "published_date": null,
      "video_id": null
    },
    {
      "id": 35,
      "title": "Caller ID Changed Everything",
      "hook": "What Killed The Phone Prank Era...",
      "status": "pending",
      "published_date": null,
      "video_id": null
    },
    {
      "id": 36,
      "title": "Three Way Calling Drama",
      "hook": "What Starts With Three Way Calling...",
      "status": "pending",
      "published_date": null,
      "video_id": null
    },
    {
      "id": 37,
      "title": "Beepers And Numeric Codes",
      "hook": "What Do Beeper Codes Really Mean...",
      "status": "pending",
      "published_date": null,
      "video_id": null
    },
    {
      "id": 38,
      "title": "Pizza Hut Reading Rewards",
      "hook": "What Made Book It So Addictive...",
      "status": "pending",
      "published_date": null,
      "video_id": null
    },
    {
      "id": 39,
      "title": "Toys R Us Endless Aisles",
      "hook": "What Killed The Toys R Us...",
      "status": "pending",
      "published_date": null,
      "video_id": null
    },
    {
      "id": 40,
      "title": "KB Toys Mall Memories",
      "hook": "What Killed KB Toys Forever...",
      "status": "pending",
      "published_date": null,
      "video_id": null
    },
    {
      "id": 41,
      "title": "Circuit City Electronics Wonderland",
      "hook": "What Killed Circuit City Forever...",
      "status": "pending",
      "published_date": null,
      "video_id": null
    },
    {
      "id": 42,
      "title": "CompUSA Overwhelming Confusion",
      "hook": "What Happened To CompUSA Suddenly...",
      "status": "pending",
      "published_date": null,
      "video_id": null
    },
    {
      "id": 43,
      "title": "Hollywood Video Last Resort",
      "hook": "What Killed Hollywood Video First...",
      "status": "pending",
      "published_date": null,
      "video_id": null
    },
    {
      "id": 44,
      "title": "Borders Bookstore Hangouts",
      "hook": "What Killed Borders Bookstore Suddenly...",
      "status": "pending",
      "published_date": null,
      "video_id": null
    },
    {
      "id": 45,
      "title": "Sam Goody Music Store",
      "hook": "What Made Sam Goody CDs Cost...",
      "status": "pending",
      "published_date": null,
      "video_id": null
    },
    {
      "id": 46,
      "title": "Tower Records Concert Tickets",
      "hook": "What Made Tower Records Tickets Impossible...",
      "status": "pending",
      "published_date": null,
      "video_id": null
    },
    {
      "id": 47,
      "title": "Suncoast Motion Picture Company",
      "hook": "What Were Suncoast VHS Prices...",
      "status": "pending",
      "published_date": null,
      "video_id": null
    },
    {
      "id": 48,
      "title": "FYE Mall Music Madness",
      "hook": "What Kept FYE Mall Alive...",
      "status": "pending",
      "published_date": null,
      "video_id": null
    },
    {
      "id": 49,
      "title": "Radio Shack Weird Survival",
      "hook": "What Did Radio Shack Always Sell...",
      "status": "pending",
      "published_date": null,
      "video_id": null
    },
    {
      "id": 50,
      "title": "Payphone Quarter Hoarding",
      "hook": "What Happens When You Hoard Quarters...",
      "status": "pending",
      "published_date": null,
      "video_id": null
    },
    {
      "id": 51,
      "title": "Collect Call Secret Messages",
      "hook": "What Secrets Hide In Collect Calls...",
      "status": "pending",
      "published_date": null,
      "video_id": null
    },
    {
      "id": 52,
      "title": "Pagers At Movie Theater",
      "hook": "What Replaced Pagers At Theaters...",
      "status": "pending",
      "published_date": null,
      "video_id": null
    },
    {
      "id": 53,
      "title": "Trapper Keeper Organization",
      "hook": "What Can Trapper Keepers Never Organize...",
      "status": "pending",
      "published_date": null,
      "video_id": null
    },
    {
      "id": 54,
      "title": "Lisa Frank Everything Explosion",
      "hook": "What Killed The Lisa Frank Empire...",
      "status": "pending",
      "published_date": null,
      "video_id": null
    },
    {
      "id": 55,
      "title": "Gel Pens Obsession Phase",
      "hook": "What Killed The Gel Pen Craze...",
      "status": "pending",
      "published_date": null,
      "video_id": null
    },
    {
      "id": 56,
      "title": "Scented Markers Sniffing",
      "hook": "What Makes Scented Markers So Addictive...",
      "status": "pending",
      "published_date": null,
      "video_id": null
    },
    {
      "id": 57,
      "title": "Overhead Projector Presentations",
      "hook": "What Killed The Overhead Projector...",
      "status": "pending",
      "published_date": null,
      "video_id": null
    },
    {
      "id": 58,
      "title": "Parachute Day Gym Class",
      "hook": "What Happens When Parachutes Fail...",
      "status": "pending",
      "published_date": null,
      "video_id": null
    },
    {
      "id": 59,
      "title": "Scooter Boards Finger Destruction",
      "hook": "What Destroys Fingers On Scooter Boards...",
      "status": "pending",
      "published_date": null,
      "video_id": null
    },
    {
      "id": 60,
      "title": "Climbing Rope Gym Challenge",
      "hook": "What Makes Climbing Ropes Impossible...",
      "status": "pending",
      "published_date": null,
      "video_id": null
    },
    {
      "id": 61,
      "title": "Presidential Fitness Test Trauma",
      "hook": "What Traumatized Kids In Gym Class...",
      "status": "pending",
      "published_date": null,
      "video_id": null
    },
    {
      "id": 62,
      "title": "MASH Fortune Telling Game",
      "hook": "What Will MASH Predict About You...",
      "status": "pending",
      "published_date": null,
      "video_id": null
    },
    {
      "id": 63,
      "title": "Cootie Catcher Paper Folding",
      "hook": "What Fortunes Do Cootie Catchers Reveal...",
      "status": "pending",
      "published_date": null,
      "video_id": null
    },
    {
      "id": 64,
      "title": "Friendship Bracelet Making",
      "hook": "What Takes 100 Hours To Make...",
      "status": "pending",
      "published_date": null,
      "video_id": null
    },
    {
      "id": 65,
      "title": "Pogs Collecting Craze",
      "hook": "What Made Pogs Worth Millions...",
      "status": "pending",
      "published_date": null,
      "video_id": null
    },
    {
      "id": 66,
      "title": "Beanie Babies Investment Scam",
      "hook": "What Made Beanie Babies Worthless...",
      "status": "pending",
      "published_date": null,
      "video_id": null
    },
    {
      "id": 67,
      "title": "Pokemon Card First Edition Hunt",
      "hook": "What Makes First Edition Pokemon Rare...",
      "status": "pending",
      "published_date": null,
      "video_id": null
    },
    {
      "id": 68,
      "title": "Yu-Gi-Oh Card Playground Battles",
      "hook": "What YuGiOh Cards Cant Kids Use...",
      "status": "pending",
      "published_date": null,
      "video_id": null
    },
    {
      "id": 69,
      "title": "Magic The Gathering Complexity",
      "hook": "What Makes Magic Cards So Confusing...",
      "status": "pending",
      "published_date": null,
      "video_id": null
    },
    {
      "id": 70,
      "title": "Furby Nightmare Possession",
      "hook": "What Happens When Furbys Never Stop...",
      "status": "pending",
      "published_date": null,
      "video_id": null
    },
    {
      "id": 71,
      "title": "Tickle Me Elmo Stampede",
      "hook": "What Caused Elmo Riots Never...",
      "status": "pending",
      "published_date": null,
      "video_id": null
    },
    {
      "id": 72,
      "title": "Bop It Frustration Game",
      "hook": "What Makes Bop It Impossible...",
      "status": "pending",
      "published_date": null,
      "video_id": null
    },
    {
      "id": 73,
      "title": "Simon Says Electronic Memory",
      "hook": "What Cant Simon Says Remember...",
      "status": "pending",
      "published_date": null,
      "video_id": null
    },
    {
      "id": 74,
      "title": "Skip It Ankle Breaker",
      "hook": "What Makes Skip It So Deadly...",
      "status": "pending",
      "published_date": null,
      "video_id": null
    },
    {
      "id": 75,
      "title": "Moon Shoes Broken Ankles",
      "hook": "What Causes Moon Shoes Broken Ankles...",
      "status": "pending",
      "published_date": null,
      "video_id": null
    },
    {
      "id": 76,
      "title": "Socker Boppers Violence",
      "hook": "What Makes Socker Boppers So Violent...",
      "status": "pending",
      "published_date": null,
      "video_id": null
    },
    {
      "id": 77,
      "title": "Super Soaker Water Wars",
      "hook": "What Started The Super Soaker Wars...",
      "status": "pending",
      "published_date": null,
      "video_id": null
    },
    {
      "id": 78,
      "title": "Slip N Slide Injuries",
      "hook": "What Happens When You Use Slip...",
      "status": "pending",
      "published_date": null,
      "video_id": null
    },
    {
      "id": 79,
      "title": "Easy Bake Oven Tiny Food",
      "hook": "What Can You Cook In Minutes...",
      "status": "pending",
      "published_date": null,
      "video_id": null
    },
    {
      "id": 80,
      "title": "Creepy Crawlers Bug Maker",
      "hook": "What Killed Every Creepy Crawlers Kid...",
      "status": "pending",
      "published_date": null,
      "video_id": null
    },
    {
      "id": 81,
      "title": "Lite Brite Choking Hazard",
      "hook": "What Happens When Kids Swallow Lite...",
      "status": "pending",
      "published_date": null,
      "video_id": null
    },
    {
      "id": 82,
      "title": "Etch A Sketch Impossible Art",
      "hook": "What Cant Be Drawn On Etch...",
      "status": "pending",
      "published_date": null,
      "video_id": null
    },
    {
      "id": 83,
      "title": "Viewmaster 3D Slides",
      "hook": "What Made Viewmaster 3D Slides Impossible...",
      "status": "pending",
      "published_date": null,
      "video_id": null
    },
    {
      "id": 84,
      "title": "Polaroid Instant Camera Magic",
      "hook": "What Made Polaroids So Expensive...",
      "status": "pending",
      "published_date": null,
      "video_id": null
    },
    {
      "id": 85,
      "title": "Film Camera 24 Exposure Limit",
      "hook": "Why Only 24 Shots On Film...",
      "status": "pending",
      "published_date": null,
      "video_id": null
    },
    {
      "id": 86,
      "title": "Double Print Photo Doubles",
      "hook": "What Causes Double Print Photo Dupes...",
      "status": "pending",
      "published_date": null,
      "video_id": null
    },
    {
      "id": 87,
      "title": "Photo Album Sticky Pages",
      "hook": "What Traps Memories In Old Albums...",
      "status": "pending",
      "published_date": null,
      "video_id": null
    },
    {
      "id": 88,
      "title": "Mall Photo Booth Strips",
      "hook": "What Happens In Mall Photo Booths...",
      "status": "pending",
      "published_date": null,
      "video_id": null
    },
    {
      "id": 89,
      "title": "Glamour Shots Awkward Photos",
      "hook": "What Makes Glamour Shots So Awkward...",
      "status": "pending",
      "published_date": null,
      "video_id": null
    },
    {
      "id": 90,
      "title": "Olan Mills Family Portraits",
      "hook": "What Made Olan Mills Portraits So...",
      "status": "pending",
      "published_date": null,
      "video_id": null
    },
    {
      "id": 91,
      "title": "JCPenney Portrait Studio",
      "hook": "What Made JCPenney Portraits So Awkward...",
      "status": "pending",
      "published_date": null,
      "video_id": null
    },
    {
      "id": 92,
      "title": "School Picture Day Hair Disaster",
      "hook": "What Happens When Hair Cant...",
      "status": "pending",
      "published_date": null,
      "video_id": null
    },
    {
      "id": 93,
      "title": "Laser Background School Photos",
      "hook": "What Made Laser Backgrounds So Popular...",
      "status": "pending",
      "published_date": null,
      "video_id": null
    },
    {
      "id": 94,
      "title": "Yearbook Signing Goodbye Messages",
      "hook": "What Secrets Do Yearbook Messages Hide...",
      "status": "pending",
      "published_date": null,
      "video_id": null
    },
    {
      "id": 95,
      "title": "Passed Notes Folding Techniques",
      "hook": "What Folds Get You Caught...",
      "status": "pending",
      "published_date": null,
      "video_id": null
    },
    {
      "id": 96,
      "title": "Book Covers From Paper Bags",
      "hook": "What Makes Paper Bag Covers Fail...",
      "status": "pending",
      "published_date": null,
      "video_id": null
    },
    {
      "id": 97,
      "title": "Pencil Grip Rubber Thing",
      "hook": "What Do Pencil Grips Really Fix...",
      "status": "pending",
      "published_date": null,
      "video_id": null
    },
    {
      "id": 98,
      "title": "Pencil Sharpener Hand Crank",
      "hook": "What Eats Pencils In Seconds...",
      "status": "pending",
      "published_date": null,
      "video_id": null
    },
    {
      "id": 99,
      "title": "Mechanical Pencil Lead Breaking",
      "hook": "What Causes Pencil Lead To Always...",
      "status": "pending",
      "published_date": null,
      "video_id": null
    }
  ]
}
